OpenGLRenderer/__init__.py
OpenGLRenderer/renderer.py
OpenGLRenderer/scene_tools.py
OpenGLRenderer-0.1.dist-info/LICENSE
OpenGLRenderer-0.1.dist-info/METADATA
OpenGLRenderer-0.1.dist-info/WHEEL
OpenGLRenderer-0.1.dist-info/top_level.txt
OpenGLRenderer-0.1.dist-info/RECORD
